.gitignore
CHANGELOG.md
DEVELOP.md
Dockerfile
LICENSE.txt
Makefile
README.md
RELEASE.md
environment.yml
pyproject.toml
requirements-package.txt
requirements.txt
setup.cfg
setup.py
examples/Pancreas.py
examples/iris.ipynb
examples/plot_algorithm_comparison.py
examples/unexact_simulation.py
gtsne/__init__.py
gtsne/_generated_version.py
gtsne/_st_gtsne.py
gtsne/st_gtsne.pyx
gtsne.egg-info/PKG-INFO
gtsne.egg-info/SOURCES.txt
gtsne.egg-info/dependency_links.txt
gtsne.egg-info/not-zip-safe
gtsne.egg-info/requires.txt
gtsne.egg-info/top_level.txt
gtsne/includes/st_gtsne/LICENSE
gtsne/includes/st_gtsne/gtsne.cpp
gtsne/includes/st_gtsne/gtsne.h
gtsne/includes/st_gtsne/quadtree.cpp
gtsne/includes/st_gtsne/quadtree.h
gtsne/includes/st_gtsne/vptree.h